devxblog_theme_kit/__init__.py
devxblog_theme_kit/cli.py
devxblog_theme_kit/views.py
devxblog_theme_kit-0.2.0.dist-info/METADATA
devxblog_theme_kit-0.2.0.dist-info/WHEEL
devxblog_theme_kit-0.2.0.dist-info/entry_points.txt
devxblog_theme_kit-0.2.0.dist-info/top_level.txt
devxblog_theme_kit-0.2.0.dist-info/RECORD
