Metadata-Version: 2.1
Name: devxblog-theme-kit
Version: 0.2.0
Summary: UNKNOWN
Home-page: UNKNOWN
Author: UNKNOWN
Author-email: UNKNOWN
License: UNKNOWN
Platform: UNKNOWN
Requires-Dist: click (==8.1.3)
Requires-Dist: django (==4.0.2)
Requires-Dist: rich (==12.4.4)
Requires-Dist: requests (==2.27.1)
Requires-Dist: pyyaml (==6)
Requires-Dist: twine (==4.0.1)
Requires-Dist: bump2version (==1.0.1)
Requires-Dist: jsonschema
Requires-Dist: pyyaml
